codetalk/__init__.py
codetalk/asset.py
codetalk/backend.py
codetalk/config.py
codetalk/filtration.py
codetalk/formatter.py
codetalk/index.py
codetalk/logconf.py
codetalk/main.py
codetalk/spinner.py
codetalk/subcommand.py
codetalk/assets/logo.txt
codetalk/assets/version.txt
navajo/__init__.py
navajo/asset.py
navajo/backend.py
navajo/config.py
navajo/filtration.py
navajo/formatter.py
navajo/index.py
navajo/logconf.py
navajo/main.py
navajo/spinner.py
navajo/subcommand.py
navajo/assets/logo.txt
navajo/assets/version.txt
navajo/server/__init__.py
navajo/server/api.py
navajo/server/chat.py
navajo/server/database.py
navajo/server/dependency.py
navajo/server/index.py
navajo/server/logconf.py
navajo/server/prompt.py
navajo/server/server.py
navajo/server/split.py
navajo/server/vector.py
navajo/server/prompts/ack_block.txt
navajo/server/prompts/ack_code.txt
navajo/server/prompts/code_summary.txt
navajo/server/prompts/system_query.txt
src/__init__.py
src/backend.py
src/config.py
src/filtration.py
src/formatter.py
src/index.py
src/logconf.py
src/main.py
src/spinner.py
src/subcommand.py
navajo-0.4.1.dist-info/LICENSE.txt
navajo-0.4.1.dist-info/METADATA
navajo-0.4.1.dist-info/WHEEL
navajo-0.4.1.dist-info/entry_points.txt
navajo-0.4.1.dist-info/top_level.txt
navajo-0.4.1.dist-info/RECORD
