Metadata-Version: 2.1
Name: navajo
Version: 0.4.1
Summary: Talk to your code!
License-File: LICENSE.txt
Requires-Dist: filetype
Requires-Dist: gitpython
Requires-Dist: prompt-toolkit
Requires-Dist: pygments
Requires-Dist: requests
Requires-Dist: backoff
Requires-Dist: cachetools
Requires-Dist: flask
Requires-Dist: numpy
Requires-Dist: openai
Requires-Dist: openai[datalib]
Requires-Dist: parse
Requires-Dist: pyjwt
Requires-Dist: sseclient-py
Requires-Dist: tiktoken
Requires-Dist: tqdm
